[{"name":"心得","path":"api/categories/心得.json","slug":"心得","count":3},{"name":"C语言","path":"api/categories/C语言.json","slug":"C语言","count":1},{"name":"MISC","path":"api/categories/MISC.json","slug":"MISC","count":2},{"name":"PWN","path":"api/categories/PWN.json","slug":"PWN","count":1},{"name":"生活","path":"api/categories/生活.json","slug":"生活","count":1},{"name":"刷题","path":"api/categories/刷题.json","slug":"刷题","count":6},{"name":"学习记录","path":"api/categories/学习记录.json","slug":"学习记录","count":2},{"name":"pwn","path":"api/categories/pwn.json","slug":"pwn","count":1}]